django_admin_testutils/__init__.py
django_admin_testutils/runner.py
django_admin_testutils/runtests.py
django_admin_testutils/selenium.py
django_admin_testutils/settings.py
django_admin_testutils/testcases.py
django_admin_testutils/urls.py
django_admin_testutils/utils.py
django_admin_testutils/static/admin_testutils/blank.html
django_admin_testutils/templates/404.html
django_admin_testutils/templates/500.html
django_admin_testutils/tests/__init__.py
django_admin_testutils/tests/admin.py
django_admin_testutils/tests/models.py
django_admin_testutils/tests/settings.py
django_admin_testutils/tests/test.py
django_admin_testutils-1.0.8.dist-info/DESCRIPTION.rst
django_admin_testutils-1.0.8.dist-info/METADATA
django_admin_testutils-1.0.8.dist-info/RECORD
django_admin_testutils-1.0.8.dist-info/WHEEL
django_admin_testutils-1.0.8.dist-info/metadata.json
django_admin_testutils-1.0.8.dist-info/top_level.txt
